airtable_schema/__init__.py
airtable_schema/cli.py
airtable_schema/fetch.py
airtable_schema/schema.py
airtable_schema-0.2.0.dist-info/entry_points.txt
airtable_schema-0.2.0.dist-info/LICENSE
airtable_schema-0.2.0.dist-info/WHEEL
airtable_schema-0.2.0.dist-info/METADATA
airtable_schema-0.2.0.dist-info/RECORD
