Metadata-Version: 2.1
Name: airtable-schema
Version: 0.2.0
Summary: Schema management for Airtable
Home-page: https://github.com/buckley-w-david/airtable-schema
License: MIT
Author: David Buckley
Author-email: buckley.w.david@gmail.com
Requires-Python: >=3.6,<4.0
Classifier: License :: OSI Approved :: MIT License
Classifier: Programming Language :: Python :: 3
Classifier: Programming Language :: Python :: 3.6
Classifier: Programming Language :: Python :: 3.7
Provides-Extra: selenium
Requires-Dist: click (>=6.7,<7.0)
Requires-Dist: selenium (>=3.13,<4.0); extra == "selenium"
